<!DOCTYPE struts PUBLIC
 "-//Apache Software Foundation//DTD Struts Configuration 2.3//EN"
 "http://struts.apache.org/dtds/struts-2.3.dtd">
<struts>
	<package name="{http://admin}admin$express"
		extends="{http://admin}admin$framework" namespace="/express">

		<action name="index" class="expressAction" method="index">
			<result name="success">/admin/express/index.vm</result>
		</action>
		
		<action name="ship" class="expressAction" method="ship">
			<result name="success">/admin/express/ship.vm</result>
		</action>
		
		<action name="waybill" class="expressAction" method="waybill">
			<result name="success">/admin/express/waybill.vm</result>
		</action>
		
		<action name="rate" class="expressAction" method="rate">
			<result name="success">/admin/express/rate.vm</result>
		</action>
		
		<action name="time" class="expressAction" method="time">
			<result name="success">/admin/express/time.vm</result>
		</action>
		
		<action name="store" class="expressAction" method="store">
			<result name="success">/admin/express/store.vm</result>
		</action>
		
		<action name="range" class="expressAction" method="range">
			<result name="success">/admin/express/range.vm</result>
		</action>
		
	</package>
</struts>